{
  "$schema": "https://nitro.margelo.com/nitro.schema.json",
  "cxxNamespace": ["systemnavigationbar"],
  "ios": {
    "iosModuleName": "NitroSystemNavigationBar"
  },
  "android": {
    "androidNamespace": ["systemnavigationbar"],
    "androidCxxLibName": "NitroSystemNavigationBar"
  },
  "autolinking": {
    "NitroSystemNavigationBar": {
      "swift": "NitroSystemNavigationBar",
      "kotlin": "NitroSystemNavigationBar"
    }
  },
  "ignorePaths": ["**/node_modules"],
  "gitAttributesGeneratedFlag": false
}
